{
    "Dataset": "obesity",
    "Classes": 7,
    "Features": 31,
    "CurrentRows": 1000,
    "OriginalRows": 2111,
    "DELIN - acc": 0.7070000000000001,
    "DELIN - balacc": 0.6991723456255476,
    "DELIN - microf1": 0.707,
    "DELIN - macrof1": 0.6813966053099456,
    "DELIN - time": 11.871999263763428,
    "RRLClassifier - acc": 0.8210000000000001,
    "RRLClassifier - balacc": 0.814482538078597,
    "RRLClassifier - microf1": 0.8210000000000001,
    "RRLClassifier - macrof1": 0.8099161519409126,
    "RRLClassifier - time": 16.040861129760742,
    "WeaklySupervisedKNeighborsClassifier - acc": 0.735,
    "WeaklySupervisedKNeighborsClassifier - balacc": 0.7287653452185472,
    "WeaklySupervisedKNeighborsClassifier - microf1": 0.735,
    "WeaklySupervisedKNeighborsClassifier - macrof1": 0.7163088218960828,
    "WeaklySupervisedKNeighborsClassifier - time": 0.04981064796447754,
    "WeaklySupervisedKRadiusClassifier - acc": 0.175,
    "WeaklySupervisedKRadiusClassifier - balacc": 0.14285714285714285,
    "WeaklySupervisedKRadiusClassifier - microf1": 0.175,
    "WeaklySupervisedKRadiusClassifier - macrof1": 0.0425531914893617,
    "WeaklySupervisedKRadiusClassifier - time": 0.06434798240661621,
    "GRMLogistic - acc": 0.131,
    "GRMLogistic - balacc": 0.14285714285714285,
    "GRMLogistic - microf1": 0.131,
    "GRMLogistic - macrof1": 0.033092555567312894,
    "GRMLogistic - time": 256.84275221824646,
    "GRMSVM - acc": 0.131,
    "GRMSVM - balacc": 0.14285714285714285,
    "GRMSVM - microf1": 0.131,
    "GRMSVM - macrof1": 0.033092555567312894,
    "GRMSVM - time": 259.69583320617676,
    "PseudoLabelsClassifier - acc": 0.648,
    "PseudoLabelsClassifier - balacc": 0.6393304943551248,
    "PseudoLabelsClassifier - microf1": 0.648,
    "PseudoLabelsClassifier - macrof1": 0.6108314115939505,
    "PseudoLabelsClassifier - time": 24.417524576187134
}